fastocr/__init__.py
fastocr/__main__.py
fastocr/base.py
fastocr/bus.py
fastocr/consts.py
fastocr/data/FastOCR.desktop
fastocr/data/config.example.ini
fastocr/data/i18n.pro
fastocr/data/introspection.xml
fastocr/grabber.py
fastocr/i18n/zh_cn.qm
fastocr/i18n/zh_cn.ts
fastocr/i18n.py
fastocr/log.py
fastocr/qml/component/About.qml
fastocr/qml/component/ActionWizard.qml
fastocr/qml/component/Actions.qml
fastocr/qml/component/Setting.qml
fastocr/qml/dummydata/backend.qml
fastocr/qml/main.qml
fastocr/resource/icon/dark/fastocr-tray.png
fastocr/resource/icon/dark/fastocr-tray.svg
fastocr/resource/icon/light/fastocr-tray.png
fastocr/resource/icon/light/fastocr-tray.svg
fastocr/service.py
fastocr/setting.py
fastocr/tray.py
fastocr/util.py
fastocr-0.3.8.dist-info/LICENSE
fastocr-0.3.8.dist-info/METADATA
fastocr-0.3.8.dist-info/WHEEL
fastocr-0.3.8.dist-info/entry_points.txt
fastocr-0.3.8.dist-info/RECORD
