Metadata-Version: 2.3
Name: fastocr
Version: 0.3.8
Summary: FastOCR is a desktop application for OCR API.
License: LGPL-3.0-only
Keywords: ocr
Author: Bruce Zhang
Author-email: zttt183525594@gmail.com
Requires-Python: >=3.11,<4.0
Classifier: License :: OSI Approved :: GNU Lesser General Public License v3 (LGPLv3)
Classifier: Programming Language :: Python :: 3
Classifier: Programming Language :: Python :: 3.11
Classifier: Programming Language :: Python :: 3.12
Classifier: Programming Language :: Python :: 3.13
Requires-Dist: PyQt6
Requires-Dist: aiohttp
Requires-Dist: click
Requires-Dist: dbus-next ; sys_platform == "linux"
Requires-Dist: qasync
Project-URL: Documentation, https://github.com/BruceZhang1993/FastOCR
Project-URL: Homepage, https://github.com/BruceZhang1993/FastOCR
Project-URL: Repository, https://github.com/BruceZhang1993/FastOCR
